dbi/__init__.py
dbi/dbi.py
dbi/demo.py
dbi/test_dbi.py
dbi/test_demo.py
qwerty-1.2.1.dist-info/DESCRIPTION.rst
qwerty-1.2.1.dist-info/METADATA
qwerty-1.2.1.dist-info/RECORD
qwerty-1.2.1.dist-info/WHEEL
qwerty-1.2.1.dist-info/entry_points.txt
qwerty-1.2.1.dist-info/metadata.json
qwerty-1.2.1.dist-info/top_level.txt
source/__init__.py
source/dbi.py
source/dbi_script.py
source/demo.py
source/test_dbi.py
source/test_dbi_script.py
source/test_demo.py
