Metadata-Version: 2.0
Name: qwerty
Version: 1.2.1
Summary: debugging interface module
Home-page: https://github.com/DrTexxOfficial/qwerty
Author: Denver P
Author-email: UNKNOWN
License: UNKNOWN
Project-URL: Source, https://github.com/DrTexxOfficial/qwerty/
Project-URL: Bug Reports, https://github.com/DrTexxOfficial/qwerty/issues
Keywords: debugging bug testing color colour terminal
Platform: UNKNOWN
Classifier: Development Status :: 5 - Production/Stable
Classifier: Intended Audience :: Developers
Classifier: Topic :: Software Development :: Debuggers
Classifier: License :: OSI Approved :: GNU General Public License v3 or later (GPLv3+)
Classifier: Programming Language :: Python :: 3.5
Requires-Dist: colorama (==0.4.1)
